pydocxrunner.py
pydocxrunner-0.0.3.dist-info/LICENSE
pydocxrunner-0.0.3.dist-info/METADATA
pydocxrunner-0.0.3.dist-info/WHEEL
pydocxrunner-0.0.3.dist-info/entry_points.txt
pydocxrunner-0.0.3.dist-info/top_level.txt
pydocxrunner-0.0.3.dist-info/RECORD
