Metadata-Version: 2.1
Name: pydocxrunner
Version: 0.0.3
Summary: Make .docx files executable for the python interpreter
Home-page: https://github.com/bennr01/pydocxrunner
Author: bennr01
License: UNKNOWN
Keywords: docx executable
Platform: UNKNOWN
Classifier: Development Status :: 4 - Beta
Classifier: License :: OSI Approved :: MIT License
Classifier: Operating System :: OS Independent
Classifier: Programming Language :: Python :: 3 :: Only
Classifier: Topic :: Utilities
Provides-Extra: testing
Requires-Dist: tox ; extra == 'testing'
